Metadata-Version: 2.4
Name: mantis-adapt
Version: 3.1.0b3
Summary: Adapt
Author-email: Hamza Mostafa <hamza.oruba@gmail.com>
License: MIT License
Project-URL: homepage, https://github.com/metis-mantis/adapt
Classifier: Development Status :: 3 - Alpha
Classifier: Intended Audience :: Science/Research
Classifier: Operating System :: POSIX :: Linux
Classifier: Programming Language :: Python :: 3
Requires-Python: <3.15,>=3.10
License-File: LICENSE
Requires-Dist: openai>=0.28.1
Requires-Dist: regex>=2023.10.3
Requires-Dist: orjson>=3.9.0
Requires-Dist: tqdm>=4.66.1
Requires-Dist: requests>=2.31.0
Requires-Dist: optuna>=3.4.0
Requires-Dist: pydantic>=2.0
Requires-Dist: litellm>=1.64.0
Requires-Dist: diskcache>=5.6.0
Requires-Dist: json-repair>=0.54.2
Requires-Dist: tenacity>=8.2.3
Requires-Dist: anyio
Requires-Dist: asyncer==0.0.8
Requires-Dist: cachetools>=5.5.0
Requires-Dist: cloudpickle>=3.0.0
Requires-Dist: numpy>=1.26.0
Requires-Dist: xxhash>=3.5.0
Requires-Dist: gepa[dspy]==0.0.22
Provides-Extra: anthropic
Requires-Dist: anthropic<1.0.0,>=0.18.0; extra == "anthropic"
Provides-Extra: weaviate
Requires-Dist: weaviate-client~=4.5.4; extra == "weaviate"
Provides-Extra: mcp
Requires-Dist: mcp; python_version >= "3.10" and extra == "mcp"
Provides-Extra: langchain
Requires-Dist: langchain_core; extra == "langchain"
Provides-Extra: dev
Requires-Dist: pytest>=6.2.5; extra == "dev"
Requires-Dist: pytest-mock>=3.12.0; extra == "dev"
Requires-Dist: pytest-asyncio>=0.26.0; extra == "dev"
Requires-Dist: ruff>=0.3.0; extra == "dev"
Requires-Dist: pre-commit>=3.7.0; extra == "dev"
Requires-Dist: pillow>=10.1.0; extra == "dev"
Requires-Dist: datamodel_code_generator>=0.26.3; extra == "dev"
Requires-Dist: build>=1.0.3; extra == "dev"
Requires-Dist: litellm>=1.64.0; (sys_platform == "win32" or python_version == "3.14") and extra == "dev"
Requires-Dist: litellm[proxy]>=1.64.0; (sys_platform != "win32" and python_version < "3.14") and extra == "dev"
Provides-Extra: test-extras
Requires-Dist: mcp; python_version >= "3.10" and extra == "test-extras"
Requires-Dist: datasets>=2.14.6; extra == "test-extras"
Requires-Dist: pandas>=2.1.1; extra == "test-extras"
Requires-Dist: optuna>=3.4.0; extra == "test-extras"
Requires-Dist: langchain_core; extra == "test-extras"
Dynamic: license-file
